{"object":"list","results":[{"object":"page","id":"34da3158-59b4-8005-9a45-f9030e1a0971","created_time":"2026-04-25T21:13:00.000Z","last_edited_time":"2026-04-25T21:31:00.000Z","created_by":{"object":"user","id":"1ded872b-594c-81c0-8ca5-0002222791e9"},"last_edited_by":{"object":"user","id":"1ded872b-594c-81c0-8ca5-0002222791e9"},"cover":null,"icon":null,"parent":{"type":"page_id","page_id":"335a3158-59b4-81eb-93ff-dd678a357924"},"in_trash":false,"is_archived":false,"is_locked":false,"properties":{"title":{"id":"title","type":"title","title":[{"type":"text","text":{"content":"Ryan Meeting 4/29 talking Points","link":null},"annotations":{"bold":false,"italic":false,"strikethrough":false,"underline":false,"code":false,"color":"default"},"plain_text":"Ryan Meeting 4/29 talking Points","href":null}]}},"url":"https://www.notion.so/Ryan-Meeting-4-29-talking-Points-34da315859b480059a45f9030e1a0971","public_url":null,"archived":false},{"object":"page","id":"34aa3158-59b4-80c7-92dc-c3ebd6820c98","created_time":"2026-04-22T01:05:00.000Z","last_edited_time":"2026-04-24T03:28:00.000Z","created_by":{"object":"user","id":"1ded872b-594c-81c0-8ca5-0002222791e9"},"last_edited_by":{"object":"user","id":"342a3158-59b4-81c2-a354-002756ca10ab"},"cover":null,"icon":null,"parent":{"type":"page_id","page_id":"335a3158-59b4-814e-aa87-df56b4c3bb73"},"in_trash":false,"is_archived":false,"is_locked":false,"properties":{"title":{"id":"title","type":"title","title":[{"type":"text","text":{"content":"Essen Healthcare 4/21 Meeting notes with actiooanl items","link":null},"annotations":{"bold":false,"italic":false,"strikethrough":false,"underline":false,"code":false,"color":"default"},"plain_text":"Essen Healthcare 4/21 Meeting notes with actiooanl items","href":null}]}},"url":"https://www.notion.so/Essen-Healthcare-4-21-Meeting-notes-with-actiooanl-items-34aa315859b480c792dcc3ebd6820c98","public_url":null,"archived":false}],"next_cursor":null,"has_more":false,"type":"page_or_data_source","page_or_data_source":{},"request_id":"1689331a-bcf9-4c51-b619-73e845ea9944"}